azure/mgmt/recoveryservicesbackup/__init__.py
azure/mgmt/recoveryservicesbackup/_configuration.py
azure/mgmt/recoveryservicesbackup/_patch.py
azure/mgmt/recoveryservicesbackup/_recovery_services_backup_client.py
azure/mgmt/recoveryservicesbackup/_version.py
azure/mgmt/recoveryservicesbackup/py.typed
azure/mgmt/recoveryservicesbackup/_utils/__init__.py
azure/mgmt/recoveryservicesbackup/_utils/serialization.py
azure/mgmt/recoveryservicesbackup/_utils/utils.py
azure/mgmt/recoveryservicesbackup/aio/__init__.py
azure/mgmt/recoveryservicesbackup/aio/_configuration.py
azure/mgmt/recoveryservicesbackup/aio/_patch.py
azure/mgmt/recoveryservicesbackup/aio/_recovery_services_backup_client.py
azure/mgmt/recoveryservicesbackup/aio/operations/__init__.py
azure/mgmt/recoveryservicesbackup/aio/operations/_backup_engines_operations.py
azure/mgmt/recoveryservicesbackup/aio/operations/_backup_jobs_operations.py
azure/mgmt/recoveryservicesbackup/aio/operations/_backup_operation_results_operations.py
azure/mgmt/recoveryservicesbackup/aio/operations/_backup_operation_statuses_operations.py
azure/mgmt/recoveryservicesbackup/aio/operations/_backup_policies_operations.py
azure/mgmt/recoveryservicesbackup/aio/operations/_backup_protectable_items_operations.py
azure/mgmt/recoveryservicesbackup/aio/operations/_backup_protected_items_operations.py
azure/mgmt/recoveryservicesbackup/aio/operations/_backup_protection_containers_operations.py
azure/mgmt/recoveryservicesbackup/aio/operations/_backup_protection_intent_operations.py
azure/mgmt/recoveryservicesbackup/aio/operations/_backup_resource_encryption_configs_operations.py
azure/mgmt/recoveryservicesbackup/aio/operations/_backup_resource_storage_configs_non_crr_operations.py
azure/mgmt/recoveryservicesbackup/aio/operations/_backup_resource_vault_configs_operations.py
azure/mgmt/recoveryservicesbackup/aio/operations/_backup_status_operations.py
azure/mgmt/recoveryservicesbackup/aio/operations/_backup_usage_summaries_operations.py
azure_mgmt_recoveryservicesbackup-10.0.0.dist-info/licenses/LICENSE
azure_mgmt_recoveryservicesbackup-10.0.0.dist-info/licenses/LICENSE.txt
azure_mgmt_recoveryservicesbackup-10.0.0.dist-info/METADATA
azure_mgmt_recoveryservicesbackup-10.0.0.dist-info/WHEEL
azure_mgmt_recoveryservicesbackup-10.0.0.dist-info/top_level.txt
azure_mgmt_recoveryservicesbackup-10.0.0.dist-info/RECORD
